Metadata-Version: 2.1
Name: fasttext-langdetect
Version: 1.0.4
Summary: 80x faster and 95% accurate language identification with Fasttext
Home-page: https://github.com/zafercavdar/fasttext-langdetect.git
Author: Zafer Cavdar
Author-email: zafercavdar@yahoo.com
License: MIT
Download-URL: https://github.com/zafercavdar/fasttext-langdetect/archive/refs/tags/v1.0.4.tar.gz
Keywords: fasttext,langdetect,language detection,language identification
Platform: UNKNOWN
Classifier: Development Status :: 5 - Production/Stable
Classifier: Intended Audience :: Developers
Classifier: Topic :: Scientific/Engineering :: Artificial Intelligence
Classifier: Topic :: Scientific/Engineering :: Information Analysis
Classifier: License :: OSI Approved :: MIT License
Classifier: Programming Language :: Python :: 3
Classifier: Programming Language :: Python :: 3.5
Classifier: Programming Language :: Python :: 3.6
Classifier: Programming Language :: Python :: 3.7
Classifier: Programming Language :: Python :: 3.8
Classifier: Programming Language :: Python :: 3.9
License-File: LICENSE
